momos_py/__init__.py
momos_py/postgres_psycopg2.py
momos_py/read_gs.py
momos_py-0.0.2.dist-info/METADATA
momos_py-0.0.2.dist-info/WHEEL
momos_py-0.0.2.dist-info/top_level.txt
momos_py-0.0.2.dist-info/RECORD
