Metadata-Version: 2.1
Name: momos-py
Version: 0.0.2
Summary: Momos Helper Package
Home-page: UNKNOWN
Author: Shaun Chew
Author-email: shaun@momos.com
License: UNKNOWN
Keywords: python,momos,internal,postgres,googlesheet
Platform: UNKNOWN
Classifier: Programming Language :: Python :: 3
Classifier: Operating System :: MacOS :: MacOS X
Classifier: Operating System :: Microsoft :: Windows
Requires-Dist: psycopg2-binary (==2.8.6)
Requires-Dist: pandas (==2.0.3)
Requires-Dist: gspread (==4.0.1)
Requires-Dist: oauth2client (==4.1.3)
